builders.py
qiita.py
setup.py
qiita_api_wrapper.egg-info/PKG-INFO
qiita_api_wrapper.egg-info/SOURCES.txt
qiita_api_wrapper.egg-info/dependency_links.txt
qiita_api_wrapper.egg-info/requires.txt
qiita_api_wrapper.egg-info/top_level.txt