Metadata-Version: 1.1
Name: qiita-api-wrapper
Version: 0.1.0
Summary: Qiita API V2 wrapper for Python
Home-page: https://github.com/nittyan/QiitaAPI
Author: nittyan
Author-email: kaziotore@gmail.com
License: MIT
Keywords: qiita qpi web
Platform: UNKNOWN
Classifier: Development Status :: 4 - Beta
Classifier: License :: OSI Approved :: MIT License
Classifier: Programming Language :: Python :: 3.4
